bulkrequests/__init__.py
bulkrequests/cliclient.py
bulkrequests/clirequests.py
bulkrequests/constants.py
bulkrequests/dcquery.py
bulkrequests/parser.py
bulkrequests-0.0.1rc3.dist-info/LICENSE
bulkrequests-0.0.1rc3.dist-info/METADATA
bulkrequests-0.0.1rc3.dist-info/WHEEL
bulkrequests-0.0.1rc3.dist-info/entry_points.txt
bulkrequests-0.0.1rc3.dist-info/top_level.txt
bulkrequests-0.0.1rc3.dist-info/RECORD
